LICENSE
MANIFEST.in
README.md
pyproject.toml
setup.py
src/brplot/__init__.py
src/brplot/brplot.c
src/brplot.egg-info/PKG-INFO
src/brplot.egg-info/SOURCES.txt
src/brplot.egg-info/dependency_links.txt
src/brplot.egg-info/requires.txt
src/brplot.egg-info/top_level.txt