Metadata-Version: 2.4
Name: brplot
Version: 0.0.1
Summary: A fast and small plotting library
Author-email: "Branimir Ri\\v{c}ko" <rickobranimir@gmail.com>
Project-URL: Homepage, https://github.com/branc116/brplot
Project-URL: Issues, https://github.com/branc116/brplot/issues
Classifier: Programming Language :: Python :: 3
Classifier: Operating System :: OS Independent
Requires-Python: >=3.8
License-File: LICENSE
Requires-Dist: setuptools
Requires-Dist: wheel
Dynamic: license-file
